{
    "type" : "dropdown",
    "name" : "country",
    "selectType" : "single",

    "labelArr" : [{
        "name" : "primary",
        "type" : "literal",
        "value" : "country"
    }],

    "subjectData" : {
        "type" : "objProperty",
        "propertyName" : "obj.merchant.country",
        "defaultVal" : {
            "type" : "fn",
            "fnName" : "getNodeCountryISO"
        }
    },

    "baseData" : {
        "type" : "cb",
        "cbName" : "getCountryArr"
    },

    "dataPartial" : {
	"labelArr" : [{
            "name" : "primary",
            "type" : "objProperty",
            "propertyName" : "name"
	}],
        "returnVal" : {
            "type" : "objProperty",
            "propertyName" : "type"
        },
        "keys" : {
            "matchOnObjBase" : {
                "type" : "objProperty",
                "propertyName" : "type"
            },
            "matchOnObjSubject" : {
                "type" : "this"
            }
        }
    },
    
    "validation" : {
        "type": "specPattern",
        "name": "isNotEmpty",
        "errorKey" : "must_select_country"
    }
}
